{
    "01": "Additional Trade Item Description URL",
    "02": "Cash Register Description URL",
    "03": "Consumer Usage Storage Instructions URL",
    "04": "Cooking Suggestions URL",
    "05": "Customer Service URL",
    "06": "Direct Product Markings Description URL",
    "07": "Feature and Benefits URL",
    "08": "Finish Description and Image URL",
    "09": "Beauty Image URL",
    "10": "Image Information URL",
    "11": "Label Storage Information URL",
    "12": "Marketing Message URL",
    "13": "Promotion Markings URL",
    "14": "Precautionary Statement URL",
    "15": "Preparation Instructions URL",
    "16": "Product Information URL",
    "17": "Serving Suggestions URL",
    "18": "Shape Description URL",
    "19": "Warranty Information URL",
    "AA": "International Telephone Access Code",
    "AB": "Joint Facsimile and Phone Number",
    "AC": "Message Only Voice Number",
    "AD": "Delivery Location Phone",
    "AE": "Area Code",
    "AL": "Allergen Information URL",
    "AP": "Alternate Telephone",
    "AS": "Answering Service",
    "AU": "Defense Switched Network",
    "BN": "Beeper Number",
    "BR": "Brochure URL Address",
    "BT": "BTX Number",
    "CA": "Cable",
    "CI": "Conflict Mineral Information URL",
    "CM": "Certification Mark Image URL",
    "CN": "Consumer Support Phone Number",
    "CP": "Cellular Phone",
    "CS": "Allergen Consumer Support Phone Number",
    "CT": "Certification URL",
    "DN": "Defense Data Network (DDN)",
    "EA": "Internet Email Address",
    "ED": "Electronic Data Interchange Access Number",
    "EM": "Electronic Mail",
    "EN": "Full Engineering Drawing URL",
    "EX": "Telephone Extension",
    "FT": "Federal Telecommunications System (FTS)",
    "FU": "Facsimile User Identifier",
    "FX": "Facsimile",
    "HF": "Home Facsimile Number",
    "HP": "Home Phone Number",
    "IT": "International Telephone",
    "MN": "Modem Number",
    "NP": "Night Telephone",
    "OF": "Other Residential Facsimile Number",
    "OT": "Other Residential Telephone Number",
    "PA": "Appointment Phone",
    "PC": "Personal Cellular",
    "PP": "Personal Phone",
    "PS": "Packet Switching",
    "Q1": "Image Link",
    "Q2": "Image Information Link",
    "Q3": "Allergen Information Link",
    "Q4": "Warranty Information Link",
    "Q5": "Customer Service Link",
    "Q6": "Product Information Link",
    "Q7": "Organic Information Link",
    "Q8": "Organic Certification Link (agency)",
    "Q9": "Diet Type Certification Link",
    "QA": "Image Thumbnail URL",
    "R1": "Diet Type Consumer Support Phone Number",
    "R2": "Installation Video URL",
    "R3": "Technical Drawing URL",
    "R4": "Manufacturer Product Website URL",
    "R5": "Material Safety Data Sheet (MSDS or SDS) URL",
    "R6": "User Manual URL",
    "R7": "Pallet Configuration URL",
    "R8": "Product Specification URL",
    "R9": "Restrictions on Hazardous Substances (RoHS) Material Composition URL",
    "RA": "Installation Instructions URL",
    "S1": "Service Manual URL",
    "S2": "Technical Bulletin URL",
    "S3": "Video Clip URL",
    "S4": "Warranty Information Link",
    "S5": "Wiring Diagram URL",
    "SP": "Showing Phone",
    "TD": "3D Rendering URL",
    "TE": "Telephone",
    "TL": "Telex",
    "TM": "Telemail",
    "TN": "Teletex Number",
    "TS": "Text Message Address",
    "TX": "TWX",
    "UR": "Uniform Resource Locator (URL)",
    "VM": "Voice Mail",
    "WC": "Work Cellular",
    "WF": "Work Facsimile Number",
    "WP": "Work Phone Number"
}